LICENSE
MANIFEST.in
README.md
requirements.txt
setup.py
src/pii_extract_plg_presidio/__init__.py
src/pii_extract_plg_presidio/defs.py
src/pii_extract_plg_presidio/plugin_loader.py
src/pii_extract_plg_presidio.egg-info/PKG-INFO
src/pii_extract_plg_presidio.egg-info/SOURCES.txt
src/pii_extract_plg_presidio.egg-info/dependency_links.txt
src/pii_extract_plg_presidio.egg-info/entry_points.txt
src/pii_extract_plg_presidio.egg-info/requires.txt
src/pii_extract_plg_presidio.egg-info/top_level.txt
src/pii_extract_plg_presidio/app/__init__.py
src/pii_extract_plg_presidio/app/info.py
src/pii_extract_plg_presidio/resources/plugin-config-transformers.json
src/pii_extract_plg_presidio/resources/plugin-config.json
src/pii_extract_plg_presidio/resources/presidio-transformers.json
src/pii_extract_plg_presidio/task/__init__.py
src/pii_extract_plg_presidio/task/analyzer.py
src/pii_extract_plg_presidio/task/collector.py
src/pii_extract_plg_presidio/task/task.py
src/pii_extract_plg_presidio/task/utils.py