Metadata-Version: 2.1
Name: pii-extract-plg-presidio
Version: 0.3.3
Summary: Presidio plugin for PII detection
Home-page: https://github.com/piisa/pii-extract-plg-presidio
Download-URL: https://github.com/piisa/pii-extract-plg-presidio/tarball/v0.3.3
Author: Paulo Villegas
Author-email: paulo.vllgs@gmail.com
License: Apache
Keywords: PIISA, PII
Classifier: Programming Language :: Python :: 3 :: Only
Classifier: License :: OSI Approved :: Apache Software License
Classifier: Development Status :: 4 - Beta
Classifier: Topic :: Software Development :: Libraries :: Application Frameworks
Requires-Python: >=3.8
Provides-Extra: test
License-File: LICENSE
